interpol/__init__.py
interpol/_version.py
interpol/api.py
interpol/autograd.py
interpol/backend.py
interpol/bounds.py
interpol/coeff.py
interpol/iso0.py
interpol/iso1.py
interpol/jit_utils.py
interpol/jitfields.py
interpol/nd.py
interpol/pushpull.py
interpol/resize.py
interpol/restrict.py
interpol/splines.py
interpol/utils.py
interpol/tests/__init__.py
interpol/tests/test_coeff.py
interpol/tests/test_gradcheck_pushpull.py
torch_interpol-0.2.6.dist-info/LICENSE
torch_interpol-0.2.6.dist-info/METADATA
torch_interpol-0.2.6.dist-info/WHEEL
torch_interpol-0.2.6.dist-info/top_level.txt
torch_interpol-0.2.6.dist-info/RECORD
