Metadata-Version: 2.1
Name: torch-interpol
Version: 0.2.6
Summary: High-order spline interpolation in PyTorch
Home-page: UNKNOWN
Author: Yael Balbastre
Author-email: yael.balbastre@gmail.com
License: MIT
Project-URL: Source Code, https://github.com/balbasty/torch-interpol
Platform: OS Independent
Classifier: License :: OSI Approved :: MIT License
Classifier: Operating System :: OS Independent
Classifier: Programming Language :: Python :: 3
Classifier: Intended Audience :: Science/Research
Classifier: Topic :: Scientific/Engineering :: Artificial Intelligence
Classifier: Topic :: Scientific/Engineering :: Medical Science Apps.
Requires-Python: >=3.6
Requires-Dist: torch >=1.3
